crier/__init__.py
crier/checker.py
crier/cli.py
crier/config.py
crier/registry.py
crier/rewrite.py
crier/scheduler.py
crier/skill.py
crier/threading.py
crier/utils.py
crier/converters/__init__.py
crier/converters/markdown.py
crier/llm/__init__.py
crier/llm/openai_compat.py
crier/llm/provider.py
crier/platforms/__init__.py
crier/platforms/base.py
crier/platforms/bluesky.py
crier/platforms/buttondown.py
crier/platforms/devto.py
crier/platforms/discord.py
crier/platforms/ghost.py
crier/platforms/hashnode.py
crier/platforms/linkedin.py
crier/platforms/mastodon.py
crier/platforms/medium.py
crier/platforms/telegram.py
crier/platforms/threads.py
crier/platforms/twitter.py
crier/platforms/wordpress.py
crier/SKILL.md
crier-0.9.0.dist-info/METADATA
crier-0.9.0.dist-info/WHEEL
crier-0.9.0.dist-info/entry_points.txt
crier-0.9.0.dist-info/RECORD
