Metadata-Version: 2.4
Name: crier
Version: 0.9.0
Summary: Cross-post your content to dev.to, Hashnode, Medium, and more
Project-URL: Homepage, https://github.com/queelius/crier
Project-URL: Repository, https://github.com/queelius/crier
Project-URL: Issues, https://github.com/queelius/crier/issues
Author-email: Alex Towell <lex@metafunctor.com>
License-Expression: MIT
Keywords: blogging,content,cross-posting,devto,hashnode,medium
Classifier: Development Status :: 3 - Alpha
Classifier: Environment :: Console
Classifier: Intended Audience :: Developers
Classifier: License :: OSI Approved :: MIT License
Classifier: Operating System :: OS Independent
Classifier: Programming Language :: Python :: 3
Classifier: Programming Language :: Python :: 3.10
Classifier: Programming Language :: Python :: 3.11
Classifier: Programming Language :: Python :: 3.12
Classifier: Topic :: Internet
Classifier: Topic :: Utilities
Requires-Python: >=3.10
Requires-Dist: click>=8.0
Requires-Dist: dateparser>=1.1.0
Requires-Dist: pyperclip>=1.8.0
Requires-Dist: pyyaml>=6.0
Requires-Dist: questionary>=2.0
Requires-Dist: requests>=2.28
Requires-Dist: rich>=13.0
Provides-Extra: dev
Requires-Dist: pytest-cov>=4.0; extra == 'dev'
Requires-Dist: pytest>=7.0; extra == 'dev'
Requires-Dist: ruff>=0.1.0; extra == 'dev'
